MANIFEST.in
README.rst
setup.cfg
setup.py
Products/__init__.py
Products.SmartColorWidget.egg-info/PKG-INFO
Products.SmartColorWidget.egg-info/SOURCES.txt
Products.SmartColorWidget.egg-info/dependency_links.txt
Products.SmartColorWidget.egg-info/entry_points.txt
Products.SmartColorWidget.egg-info/namespace_packages.txt
Products.SmartColorWidget.egg-info/not-zip-safe
Products.SmartColorWidget.egg-info/requires.txt
Products.SmartColorWidget.egg-info/top_level.txt
Products/SmartColorWidget/Widget.py
Products/SmartColorWidget/__init__.py
Products/SmartColorWidget/config.py
Products/SmartColorWidget/configure.zcml
Products/SmartColorWidget/interfaces.py
Products/SmartColorWidget/profiles.zcml
Products/SmartColorWidget/setuphandlers.py
Products/SmartColorWidget/upgrades.py
Products/SmartColorWidget/version.txt
Products/SmartColorWidget/Extensions/install.py
Products/SmartColorWidget/browser/__init__.py
Products/SmartColorWidget/browser/configure.zcml
Products/SmartColorWidget/browser/pages.py
Products/SmartColorWidget/browser/smartcolor_helper.css.dtml
Products/SmartColorWidget/browser/smartcolorwidget-macros.pt
Products/SmartColorWidget/browser/static/color_wheel.png
Products/SmartColorWidget/browser/static/colortable.png
Products/SmartColorWidget/browser/static/cursor.gif
Products/SmartColorWidget/browser/static/hue_slide.png
Products/SmartColorWidget/browser/static/lighttable.png
Products/SmartColorWidget/browser/static/mask.png
Products/SmartColorWidget/browser/static/picker_bg.png
Products/SmartColorWidget/browser/static/slider.gif
Products/SmartColorWidget/browser/static/smartcolor_helper.js
Products/SmartColorWidget/examples/SmartColorWidgetDemoType.py
Products/SmartColorWidget/examples/__init__.py
Products/SmartColorWidget/locales/smartcolorwidget.pot
Products/SmartColorWidget/locales/update.sh
Products/SmartColorWidget/locales/fr/LC_MESSAGES/smartcolorwidget.po
Products/SmartColorWidget/locales/it/LC_MESSAGES/smartcolorwidget.po
Products/SmartColorWidget/profiles/default/browserlayer.xml
Products/SmartColorWidget/profiles/default/metadata.xml
Products/SmartColorWidget/profiles/default/smartcolorwidget.txt
Products/SmartColorWidget/profiles/uninstall/browserlayer.xml
docs/HISTORY.txt
docs/INSTALL.txt
docs/LICENSE.GPL
docs/LICENSE.txt