Metadata-Version: 1.1
Name: Products.SmartColorWidget
Version: 1.1.5
Summary: Smart color picker widget for Archetypes
Home-page: http://plone.org/products/smartcolorwidget
Author: Ingeniweb
Author-email: support@ingeniweb.com
License: GPL
Keywords: plone widget colorpicker
Platform: UNKNOWN
Classifier: Framework :: Plone
Classifier: Framework :: Plone :: 4.0
Classifier: Framework :: Plone :: 4.1
Classifier: Framework :: Plone :: 4.2
Classifier: Framework :: Plone :: 4.3
Classifier: Programming Language :: Python
Classifier: Programming Language :: Python :: 2.6
Classifier: Programming Language :: Python :: 2.7
Classifier: Topic :: Software Development :: Libraries :: Python Modules
